fixtest/__init__.py
fixtest/sample_config.py
fixtest/base/__init__.py
fixtest/base/asserts.py
fixtest/base/config.py
fixtest/base/controller.py
fixtest/base/message.py
fixtest/base/queue.py
fixtest/base/runner.py
fixtest/base/utils.py
fixtest/fix/__init__.py
fixtest/fix/constants.py
fixtest/fix/message.py
fixtest/fix/messages.py
fixtest/fix/parser.py
fixtest/fix/protocol.py
fixtest/fix/transport.py
fixtest/fix/utils.py
fixtest/simple/__init__.py
fixtest/simple/logon_controller.py
fixtest/simple/simple_base.py
fixtest/simple/simple_config.py
fixtest/simple/simple_controller.py
fixtest/simple/simple_test.py
fixtest/tests/__init__.py
fixtest/tests/base_config_test.py
fixtest/tests/base_message_test.py
fixtest/tests/fix_message_test.py
fixtest/tests/fix_parser_test.py
fixtest/tests/fix_protocol_test.py
fixtest/tests/test_config.py
fixtest/tests/utils.py
fixtest-0.2.0.dist-info/LICENSE
fixtest-0.2.0.dist-info/METADATA
fixtest-0.2.0.dist-info/WHEEL
fixtest-0.2.0.dist-info/entry_points.txt
fixtest-0.2.0.dist-info/top_level.txt
fixtest-0.2.0.dist-info/RECORD
