Metadata-Version: 2.1
Name: fixtest
Version: 0.2.0
Summary: FIX (Financial Information eXchange) protocol testing tool
Author-email: Kenn Takara <kenn.takara@outlook.com>
License: MIT License
Project-URL: Homepage, https://github.com/kennt/fixtest
Project-URL: Bug Tracker, https://github.com/kennt/fixtest/issues
Classifier: Development Status :: 3 - Alpha
Classifier: Intended Audience :: Developers
Classifier: Intended Audience :: Financial and Insurance Industry
Classifier: License :: OSI Approved :: MIT License
Classifier: Operating System :: OS Independent
Classifier: Programming Language :: Python :: 3
Classifier: Topic :: System :: Networking
Classifier: Topic :: Software Development :: Testing
Requires-Python: >=3.8
License-File: LICENSE
Requires-Dist: twisted (>=22.0.0)
